<Group>
  <ToolOneVersion>8</ToolOneVersion>
  <Groups>
    <Group>
      <Name>Targets</Name>
      <UseParentGUIDRange>1</UseParentGUIDRange>
      <FileName>data/config/game/asset/balancing_targets.xml</FileName>
    </Group>
    <Group>
      <Name>Feedback</Name>
      <UseParentGUIDRange>1</UseParentGUIDRange>
      <FileName>data/config/game/asset/balancing_feedback.xml</FileName>
    </Group>
    <Group>
      <Name>Economy</Name>
      <UseParentGUIDRange>1</UseParentGUIDRange>
      <FileName>data/config/game/asset/balancing_economy.xml</FileName>
      <SectionID>1983</SectionID>
    </Group>
    <Group>
      <Name>Population</Name>
      <UseParentGUIDRange>1</UseParentGUIDRange>
      <FileName>data/config/game/asset/balancing_population.xml</FileName>
      <SectionID>323</SectionID>
    </Group>
    <Group>
      <Name>EventSessions</Name>
      <UseParentGUIDRange>1</UseParentGUIDRange>
      <FileName>data/config/game/asset/balancing_event_sessions.xml</FileName>
    </Group>
    <Group>
      <Name>Unlocks</Name>
      <UseParentGUIDRange>1</UseParentGUIDRange>
      <FileName>data/config/game/asset/balancing_unlocks.xml</FileName>
      <SectionID>1993</SectionID>
      <DefaultTemplate>ProgressLevel</DefaultTemplate>
    </Group>
    <Group>
      <Name>UnlockTrigger</Name>
      <UseParentGUIDRange>1</UseParentGUIDRange>
      <FileName>data/config/game/asset/balancing_unlock_trigger.xml</FileName>
    </Group>
    <Group>
      <Name>Voting</Name>
      <UseParentGUIDRange>1</UseParentGUIDRange>
      <FileName>data/config/game/asset/balancing_voting.xml</FileName>
      <SectionID>1995</SectionID>
      <DefaultTemplate>VotingOption</DefaultTemplate>
    </Group>
    <Group>
      <Name>OrnamentStates</Name>
      <UseParentGUIDRange>1</UseParentGUIDRange>
      <FileName>data/config/game/asset/balancing_ornament_states.xml</FileName>
      <SectionID>2337</SectionID>
      <DefaultTemplate>OrnamentalState</DefaultTemplate>
    </Group>
    <Group>
      <Name>UI</Name>
      <UseParentGUIDRange>1</UseParentGUIDRange>
      <FileName>data/config/game/asset/balancing_ui.xml</FileName>
      <SectionID>1974</SectionID>
    </Group>
    <Group>
      <Name>HappyEvents</Name>
      <UseParentGUIDRange>1</UseParentGUIDRange>
      <DefaultTemplate>HappyEvent</DefaultTemplate>
      <Assets>
        <Asset>
          <Template>HappyEvent</Template>
          <Values>
            <HappyEvent>
              <StartDay>17</StartDay>
              <StartMonth>12</StartMonth>
              <EndDay>31</EndDay>
              <EndMonth>12</EndMonth>
            </HappyEvent>
            <Standard>
              <GUID>2002385</GUID>
              <Name>ChristmasEvent</Name>
              <Creator>jschaub</Creator>
              <CreationTime>2015-11-11 15:36</CreationTime>
              <LastChangeUser>lpieper</LastChangeUser>
              <LastChangeTime>2015-12-25 10:38</LastChangeTime>
            </Standard>
          </Values>
        </Asset>
        <Asset>
          <Template>HappyEvent</Template>
          <Values>
            <HappyEvent>
              <HappyEvent>Eastern</HappyEvent>
              <StartDay>-5</StartDay>
              <EndDay>5</EndDay>
              <RelativeToEasterSunday>1</RelativeToEasterSunday>
            </HappyEvent>
            <Standard>
              <GUID>2002386</GUID>
              <Name>EasterEvent</Name>
              <Creator>jschaub</Creator>
              <CreationTime>2015-11-11 15:37</CreationTime>
              <LastChangeUser>jschaub</LastChangeUser>
              <LastChangeTime>2015-11-11 15:37</LastChangeTime>
            </Standard>
          </Values>
        </Asset>
        <Asset>
          <Template>HappyEvent</Template>
          <Values>
            <HappyEvent>
              <HappyEvent>AnnoDay</HappyEvent>
              <StartDay>22</StartDay>
              <StartMonth>5</StartMonth>
              <EndDay>22</EndDay>
              <EndMonth>5</EndMonth>
            </HappyEvent>
            <Standard>
              <GUID>2002521</GUID>
              <Name>AnnoDayEvent</Name>
              <Creator>svelychko</Creator>
              <CreationTime>2016-04-07 18:49</CreationTime>
              <LastChangeUser>svelychko</LastChangeUser>
              <LastChangeTime>2016-04-08 14:02</LastChangeTime>
            </Standard>
          </Values>
        </Asset>
        <Asset>
          <Template>HappyEvent</Template>
          <Values>
            <HappyEvent>
              <HappyEvent>SummerEvent</HappyEvent>
              <StartDay>22</StartDay>
              <StartMonth>7</StartMonth>
              <EndDay>14</EndDay>
              <EndMonth>8</EndMonth>
            </HappyEvent>
            <Standard>
              <GUID>2002548</GUID>
              <Name>SummerEvent</Name>
              <Creator>svelychko</Creator>
              <CreationTime>2016-06-08 18:29</CreationTime>
              <LastChangeUser>svelychko</LastChangeUser>
              <LastChangeTime>2016-06-08 18:30</LastChangeTime>
            </Standard>
          </Values>
        </Asset>
      </Assets>
    </Group>
    <Group>
      <Name>WorldMarket</Name>
      <UseParentGUIDRange>1</UseParentGUIDRange>
      <Assets>
        <Asset>
          <Template>WorldMarketFeature</Template>
          <Values>
            <Standard>
              <GUID>2002398</GUID>
              <Name>WorldMarketFeature</Name>
              <Creator>mreinhardt</Creator>
              <CreationTime>2015-12-14 18:17</CreationTime>
              <LastChangeUser>sknietzsch</LastChangeUser>
              <LastChangeTime>2016-02-03 17:54</LastChangeTime>
              <ID>WorldMarketFeature</ID>
            </Standard>
            <WorldMarketFeature>
              <RouteDurationTime>43200000</RouteDurationTime>
              <RouteExpirationWarningTime>300000</RouteExpirationWarningTime>
              <RouteExpirationOfferTime>120000</RouteExpirationOfferTime>
              <NewsTicker>
                <PriceChangeText>119728</PriceChangeText>
                <PriceChangeEventText>120944</PriceChangeEventText>
                <TitleText>120799</TitleText>
                <SeparatorText>119729</SeparatorText>
                <EventDescriptionUpTextPool>2002397</EventDescriptionUpTextPool>
                <EventDescriptionDownTextPool>2002435</EventDescriptionDownTextPool>
                <EventPriceUpTextPool>2002400</EventPriceUpTextPool>
                <EventPriceDownTextPool>2002401</EventPriceDownTextPool>
              </NewsTicker>
            </WorldMarketFeature>
          </Values>
        </Asset>
        <Asset>
          <Template>TextPool</Template>
          <Values>
            <Standard>
              <GUID>2002399</GUID>
              <Name>EventActorTextPool</Name>
              <Creator>mreinhardt</Creator>
              <CreationTime>2015-12-16 14:57</CreationTime>
              <LastChangeUser>sknietzsch</LastChangeUser>
              <LastChangeTime>2016-02-18 10:05</LastChangeTime>
            </Standard>
            <TextPool />
          </Values>
        </Asset>
        <Asset>
          <Template>TextPool</Template>
          <Values>
            <Standard>
              <GUID>2002397</GUID>
              <Name>EventDescriptionUpTextPool</Name>
              <Creator>mreinhardt</Creator>
              <CreationTime>2015-12-14 18:16</CreationTime>
              <LastChangeUser>sknietzsch</LastChangeUser>
              <LastChangeTime>2016-02-18 10:05</LastChangeTime>
            </Standard>
            <TextPool>
              <TextGroups>
                <Item>
                  <Group>-515343893</Group>
                </Item>
              </TextGroups>
            </TextPool>
          </Values>
        </Asset>
        <Asset>
          <Template>TextPool</Template>
          <Values>
            <Standard>
              <GUID>2002435</GUID>
              <Name>EventDescriptionDownTextPool</Name>
              <Creator>mreinhardt</Creator>
              <CreationTime>2016-01-26 17:38</CreationTime>
              <LastChangeUser>sknietzsch</LastChangeUser>
              <LastChangeTime>2016-02-18 10:05</LastChangeTime>
            </Standard>
            <TextPool>
              <TextGroups>
                <Item>
                  <Group>1796018430</Group>
                </Item>
              </TextGroups>
            </TextPool>
          </Values>
        </Asset>
        <Asset>
          <Template>TextPool</Template>
          <Values>
            <Standard>
              <GUID>2002400</GUID>
              <Name>PriceUpTextPool</Name>
              <Creator>mreinhardt</Creator>
              <CreationTime>2015-12-16 16:50</CreationTime>
              <LastChangeUser>sknietzsch</LastChangeUser>
              <LastChangeTime>2016-02-03 17:51</LastChangeTime>
            </Standard>
            <TextPool>
              <TextGroups>
                <Item>
                  <Group>-123763795</Group>
                </Item>
              </TextGroups>
            </TextPool>
          </Values>
        </Asset>
        <Asset>
          <Template>TextPool</Template>
          <Values>
            <Standard>
              <GUID>2002401</GUID>
              <Name>PriceDownTextPool</Name>
              <Creator>mreinhardt</Creator>
              <CreationTime>2015-12-16 16:50</CreationTime>
              <LastChangeUser>sknietzsch</LastChangeUser>
              <LastChangeTime>2016-02-03 17:51</LastChangeTime>
            </Standard>
            <TextPool>
              <TextGroups>
                <Item>
                  <Group>-1934372531</Group>
                </Item>
              </TextGroups>
            </TextPool>
          </Values>
        </Asset>
      </Assets>
    </Group>
    <Group>
      <Name>Difficulty</Name>
      <UseParentGUIDRange>1</UseParentGUIDRange>
      <Assets>
        <Asset>
          <Template>DifficultyBalancing</Template>
          <Values>
            <Standard>
              <GUID>2002450</GUID>
              <Name>DifficultySettings</Name>
              <Creator>mreinhardt</Creator>
              <CreationTime>2016-02-11 18:12</CreationTime>
              <LastChangeUser>sbombera</LastChangeUser>
              <LastChangeTime>2016-08-31 13:29</LastChangeTime>
              <ID>DifficultySettings</ID>
            </Standard>
            <DifficultySettings>
              <Descriptions>
                <LossCondition>
                  <Description>116840</Description>
                  <InfoTip>121313</InfoTip>
                </LossCondition>
                <Revenue>
                  <Description>116841</Description>
                  <InfoTip>121314</InfoTip>
                </Revenue>
                <StartCredits>
                  <Description>116844</Description>
                </StartCredits>
                <ConstructionCostRefund>
                  <Description>116842</Description>
                  <InfoTip>121315</InfoTip>
                </ConstructionCostRefund>
                <DistributionCenterOutput>
                  <Description>116846</Description>
                </DistributionCenterOutput>
                <OptionalQuestFrequency>
                  <Description>116847</Description>
                </OptionalQuestFrequency>
                <OptionalQuestRewards>
                  <Description>116848</Description>
                </OptionalQuestRewards>
                <PickupQuests>
                  <Description>117972</Description>
                  <InfoTip>118384</InfoTip>
                </PickupQuests>
                <MilitaryProgress>
                  <Description>116849</Description>
                </MilitaryProgress>
                <RelocateBuildings>
                  <Description>117971</Description>
                  <InfoTip>121316</InfoTip>
                </RelocateBuildings>
                <TraderRefillRate>
                  <Description>116845</Description>
                </TraderRefillRate>
                <TraderPrices>
                  <Description>121116</Description>
                </TraderPrices>
                <DestructibleShips>
                  <Description>121117</Description>
                  <InfoTip>121186</InfoTip>
                </DestructibleShips>
                <InactiveCosts>
                  <Description>121239</Description>
                  <InfoTip>121238</InfoTip>
                </InactiveCosts>
                <OptionalQuestTimeout>
                  <Description>121214</Description>
                </OptionalQuestTimeout>
                <PermanentSectorEffects>
                  <Description>14000983</Description>
                </PermanentSectorEffects>
                <TemporaraySectorEffects>
                  <Description>14000984</Description>
                  <InfoTip>121567</InfoTip>
                </TemporaraySectorEffects>
                <NpcLevelSpeed>
                  <Description>121557</Description>
                  <InfoTip>121556</InfoTip>
                </NpcLevelSpeed>
                <Workforce>
                  <Description>13000460</Description>
                </Workforce>
                <Consumption>
                  <Description>13000461</Description>
                </Consumption>
                <MilitaryInvasions>
                  <Description>13000874</Description>
                  <InfoTip>13000784</InfoTip>
                </MilitaryInvasions>
                <MilitaryEnemyStrength>
                  <Description>13000875</Description>
                  <InfoTip>13000789</InfoTip>
                </MilitaryEnemyStrength>
                <SatisfactionInfluencesTaxes>
                  <Description>13000872</Description>
                  <InfoTip>13000920</InfoTip>
                </SatisfactionInfluencesTaxes>
                <DominanceShareBonus>
                  <Description>14001934</Description>
                  <InfoTip>13000951</InfoTip>
                </DominanceShareBonus>
              </Descriptions>
              <LossCondition>
                <BailoutWithSlowLiquidation>
                  <ValueName>117937</ValueName>
                  <BailoutLiquidationPercent>20480</BailoutLiquidationPercent>
                </BailoutWithSlowLiquidation>
                <BailoutWithFastLiquidation>
                  <ValueName>117938</ValueName>
                  <Points>10</Points>
                  <BailoutLiquidationPercent>40960</BailoutLiquidationPercent>
                </BailoutWithFastLiquidation>
                <Bankrupt>
                  <ValueName>117936</ValueName>
                  <Points>20</Points>
                </Bankrupt>
              </LossCondition>
              <Revenue>
                <Plenty>
                  <ValueName>117940</ValueName>
                  <TaxBonusPercent>204800</TaxBonusPercent>
                </Plenty>
                <Medium>
                  <ValueName>117941</ValueName>
                  <Points>30</Points>
                  <TaxBonusPercent>153600</TaxBonusPercent>
                </Medium>
                <Spare>
                  <ValueName>117942</ValueName>
                  <Points>60</Points>
                  <TaxBonusPercent>102400</TaxBonusPercent>
                </Spare>
              </Revenue>
              <StartCredits>
                <Plenty>
                  <ValueName>117940</ValueName>
                  <StartProductsPercent>819200</StartProductsPercent>
                </Plenty>
                <Medium>
                  <ValueName>117941</ValueName>
                  <Points>5</Points>
                  <StartProductsPercent>614400</StartProductsPercent>
                </Medium>
                <Spare>
                  <ValueName>117942</ValueName>
                  <Points>10</Points>
                  <StartProductsPercent>409600</StartProductsPercent>
                </Spare>
              </StartCredits>
              <ConstructionCostRefund>
                <Full>
                  <ValueName>117945</ValueName>
                  <RefundPercent>409600</RefundPercent>
                </Full>
                <Half>
                  <ValueName>117946</ValueName>
                  <Points>5</Points>
                  <RefundPercent>204800</RefundPercent>
                </Half>
                <None>
                  <ValueName>117947</ValueName>
                  <Points>10</Points>
                </None>
                <PayCredits>
                  <ValueName>121211</ValueName>
                  <Points>15</Points>
                  <FlatValue>500</FlatValue>
                  <CostPercent>40960</CostPercent>
                </PayCredits>
              </ConstructionCostRefund>
              <DistributionCenterOutput>
                <Plenty>
                  <ValueName>117940</ValueName>
                </Plenty>
                <Medium>
                  <ValueName>117941</ValueName>
                  <Points>5</Points>
                </Medium>
                <Spare>
                  <ValueName>117942</ValueName>
                  <Points>10</Points>
                </Spare>
              </DistributionCenterOutput>
              <OptionalQuestFrequency>
                <Often>
                  <ValueName>117950</ValueName>
                  <CooldownFactor>4096</CooldownFactor>
                </Often>
                <Normal>
                  <ValueName>117951</ValueName>
                  <Points>5</Points>
                  <CooldownFactor>12288</CooldownFactor>
                </Normal>
                <Off>
                  <ValueName>117952</ValueName>
                  <Points>10</Points>
                  <CooldownFactor>4096</CooldownFactor>
                  <DisabledQuestPools>
                    <Item>
                      <Pool>3001727</Pool>
                    </Item>
                  </DisabledQuestPools>
                </Off>
              </OptionalQuestFrequency>
              <OptionalQuestRewards>
                <Plenty>
                  <ValueName>117940</ValueName>
                  <RewardFactor>5120</RewardFactor>
                </Plenty>
                <Medium>
                  <ValueName>117941</ValueName>
                  <Points>5</Points>
                  <RewardFactor>4096</RewardFactor>
                </Medium>
                <Spare>
                  <ValueName>117942</ValueName>
                  <Points>10</Points>
                  <RewardFactor>3072</RewardFactor>
                </Spare>
                <PennyPinching>
                  <ValueName>121184</ValueName>
                  <Points>15</Points>
                  <RewardFactor>2048</RewardFactor>
                </PennyPinching>
              </OptionalQuestRewards>
              <PickupQuests>
                <Off>
                  <ValueName>117952</ValueName>
                  <Points>5</Points>
                  <DisabledQuestPools>
                    <Item>
                      <Pool>3001291</Pool>
                    </Item>
                  </DisabledQuestPools>
                </Off>
                <On>
                  <ValueName>117955</ValueName>
                </On>
              </PickupQuests>
              <MilitaryProgress>
                <Fast>
                  <ValueName>117957</ValueName>
                </Fast>
                <Normal>
                  <ValueName>117951</ValueName>
                  <Points>10</Points>
                </Normal>
                <Slow>
                  <ValueName>117958</ValueName>
                  <Points>20</Points>
                </Slow>
              </MilitaryProgress>
              <RelocateBuildings>
                <On>
                  <ValueName>117955</ValueName>
                  <Interval>3</Interval>
                  <FlatValue>50</FlatValue>
                  <MaxSteps>15</MaxSteps>
                  <Percentage>409600</Percentage>
                  <RoundValue>5</RoundValue>
                </On>
                <Off>
                  <ValueName>117952</ValueName>
                  <Points>10</Points>
                </Off>
                <PayCredits>
                  <ValueName>121211</ValueName>
                  <Points>5</Points>
                  <Interval>3</Interval>
                  <FlatValue>250</FlatValue>
                  <MaxSteps>20</MaxSteps>
                  <Percentage>20480</Percentage>
                  <RoundValue>5</RoundValue>
                </PayCredits>
              </RelocateBuildings>
              <TraderRefillRate2>
                <Plenty>
                  <ValueName>117940</ValueName>
                  <RefillRatePercent>409600</RefillRatePercent>
                </Plenty>
                <Medium>
                  <ValueName>117941</ValueName>
                  <Points>2</Points>
                  <RefillRatePercent>327680</RefillRatePercent>
                </Medium>
                <Sparse>
                  <ValueName>117942</ValueName>
                  <Points>5</Points>
                  <RefillRatePercent>245760</RefillRatePercent>
                </Sparse>
                <VerySparse>
                  <ValueName>121138</ValueName>
                  <Points>10</Points>
                  <RefillRatePercent>163840</RefillRatePercent>
                </VerySparse>
              </TraderRefillRate2>
              <TraderPrices>
                <Cheap>
                  <ValueName>121134</ValueName>
                  <MinOfferPricePercent>2867200</MinOfferPricePercent>
                  <MaxOfferPricePercent>3072000</MaxOfferPricePercent>
                  <MinRequestPricePercent>2457600</MinRequestPricePercent>
                  <MaxRequestPricePercent>2662400</MaxRequestPricePercent>
                </Cheap>
                <Moderate>
                  <ValueName>121135</ValueName>
                  <Points>2</Points>
                  <MinOfferPricePercent>3584000</MinOfferPricePercent>
                  <MaxOfferPricePercent>3840000</MaxOfferPricePercent>
                  <MinRequestPricePercent>2211840</MinRequestPricePercent>
                  <MaxRequestPricePercent>2396160</MaxRequestPricePercent>
                </Moderate>
                <Expensive>
                  <ValueName>121136</ValueName>
                  <Points>5</Points>
                  <MinOfferPricePercent>4300800</MinOfferPricePercent>
                  <MaxOfferPricePercent>4608000</MaxOfferPricePercent>
                  <MinRequestPricePercent>1966080</MinRequestPricePercent>
                  <MaxRequestPricePercent>2129920</MaxRequestPricePercent>
                </Expensive>
                <Overpriced>
                  <ValueName>121137</ValueName>
                  <Points>10</Points>
                  <MinOfferPricePercent>5017600</MinOfferPricePercent>
                  <MaxOfferPricePercent>5376000</MaxOfferPricePercent>
                  <MinRequestPricePercent>1720320</MinRequestPricePercent>
                  <MaxRequestPricePercent>1863680</MaxRequestPricePercent>
                </Overpriced>
              </TraderPrices>
              <DestructibleShips>
                <Off>
                  <ValueName>117955</ValueName>
                </Off>
                <On>
                  <ValueName>117952</ValueName>
                  <Points>5</Points>
                </On>
              </DestructibleShips>
              <IncreasingDistributionCenterCosts>
                <On>
                  <ExpansionTaxModifier>102</ExpansionTaxModifier>
                  <IgnoreFirstCenterInSession>1</IgnoreFirstCenterInSession>
                  <RareMaterialCostsPerCenterInRegion>102400</RareMaterialCostsPerCenterInRegion>
                  <RareMaterialTypeInRegion>
                    <Earth>
                      <RareMaterial>6000480</RareMaterial>
                    </Earth>
                    <Tundra>
                      <RareMaterial>6000482</RareMaterial>
                    </Tundra>
                    <Arctic>
                      <RareMaterial>6000482</RareMaterial>
                    </Arctic>
                    <Moon>
                      <RareMaterial>6000484</RareMaterial>
                    </Moon>
                  </RareMaterialTypeInRegion>
                </On>
              </IncreasingDistributionCenterCosts>
              <OptionalQuestTimeout>
                <NotLimited>
                  <ValueName>121215</ValueName>
                </NotLimited>
                <Long>
                  <ValueName>121216</ValueName>
                  <Points>5</Points>
                  <TimeFactor>4096</TimeFactor>
                </Long>
                <Medium>
                  <ValueName>121217</ValueName>
                  <Points>10</Points>
                  <TimeFactor>2048</TimeFactor>
                </Medium>
                <Short>
                  <ValueName>121218</ValueName>
                  <Points>15</Points>
                  <TimeFactor>1024</TimeFactor>
                </Short>
              </OptionalQuestTimeout>
              <Presets>
                <Normal>
                  <LossCondition>BailoutWithFastLiquidation</LossCondition>
                  <Revenue>Medium</Revenue>
                  <StartCredits>Medium</StartCredits>
                  <ConstructionCostRefund>Half</ConstructionCostRefund>
                  <DistributionCenterOutput>Medium</DistributionCenterOutput>
                  <OptionalQuestRewards>Medium</OptionalQuestRewards>
                  <PickupQuests>On</PickupQuests>
                  <MilitaryProgress>Normal</MilitaryProgress>
                  <RelocateBuildings>PayCredits</RelocateBuildings>
                  <TraderRefillRate>Medium</TraderRefillRate>
                  <TraderPrices>Moderate</TraderPrices>
                  <OptionalQuestTimeout>Long</OptionalQuestTimeout>
                  <PermanentSectorEffects>On</PermanentSectorEffects>
                  <TemporarySectorEffects>Seldom</TemporarySectorEffects>
                  <NpcLevelSpeed>Normal</NpcLevelSpeed>
                  <MilitarySectorEffects>Seldom</MilitarySectorEffects>
                  <Consumption>Medium</Consumption>
                  <MilitaryInvasions>Seldom</MilitaryInvasions>
                </Normal>
                <Hard>
                  <LossCondition>Bankrupt</LossCondition>
                  <Revenue>Spare</Revenue>
                  <StartCredits>Spare</StartCredits>
                  <ConstructionCostRefund>None</ConstructionCostRefund>
                  <DistributionCenterOutput>Spare</DistributionCenterOutput>
                  <OptionalQuestFrequency>Normal</OptionalQuestFrequency>
                  <OptionalQuestRewards>Spare</OptionalQuestRewards>
                  <PickupQuests>On</PickupQuests>
                  <MilitaryProgress>Slow</MilitaryProgress>
                  <RelocateBuildings>PayCredits</RelocateBuildings>
                  <TraderRefillRate>Sparse</TraderRefillRate>
                  <TraderPrices>Expensive</TraderPrices>
                  <DestructibleShips>On</DestructibleShips>
                  <OptionalQuestTimeout>Medium</OptionalQuestTimeout>
                  <InactiveCosts>On</InactiveCosts>
                  <PermanentSectorEffects>On</PermanentSectorEffects>
                  <TemporarySectorEffects>Regular</TemporarySectorEffects>
                  <NpcLevelSpeed>Fast</NpcLevelSpeed>
                  <MilitarySectorEffects>Regular</MilitarySectorEffects>
                  <Workforce>Medium</Workforce>
                  <Consumption>Medium</Consumption>
                  <MilitaryEnemyStrength>Challenging</MilitaryEnemyStrength>
                  <MilitaryInvasions>Regular</MilitaryInvasions>
                  <SatisfactionInfluencesTaxes>Medium</SatisfactionInfluencesTaxes>
                  <DominanceShareBonus>Medium</DominanceShareBonus>
                </Hard>
                <Classic>
                  <LossCondition>Bankrupt</LossCondition>
                  <Revenue>Spare</Revenue>
                  <StartCredits>Spare</StartCredits>
                  <ConstructionCostRefund>PayCredits</ConstructionCostRefund>
                  <DistributionCenterOutput>Spare</DistributionCenterOutput>
                  <OptionalQuestFrequency>Normal</OptionalQuestFrequency>
                  <OptionalQuestRewards>PennyPinching</OptionalQuestRewards>
                  <MilitaryProgress>Slow</MilitaryProgress>
                  <RelocateBuildings>Off</RelocateBuildings>
                  <TraderRefillRate>VerySparse</TraderRefillRate>
                  <TraderPrices>Overpriced</TraderPrices>
                  <DestructibleShips>On</DestructibleShips>
                  <OptionalQuestTimeout>Short</OptionalQuestTimeout>
                  <InactiveCosts>On</InactiveCosts>
                  <PermanentSectorEffects>On</PermanentSectorEffects>
                  <TemporarySectorEffects>Regular</TemporarySectorEffects>
                  <NpcLevelSpeed>Fast</NpcLevelSpeed>
                  <MilitarySectorEffects>Regular</MilitarySectorEffects>
                  <Workforce>Sparse</Workforce>
                  <Consumption>Plenty</Consumption>
                  <MilitaryEnemyStrength>Deadly</MilitaryEnemyStrength>
                  <MilitaryInvasions>Regular</MilitaryInvasions>
                  <SatisfactionInfluencesTaxes>High</SatisfactionInfluencesTaxes>
                  <DominanceShareBonus>Hard</DominanceShareBonus>
                </Classic>
                <Easy>
                  <PickupQuests>On</PickupQuests>
                  <PermanentSectorEffects>On</PermanentSectorEffects>
                </Easy>
              </Presets>
              <PointsNeeded>
                <Normal>
                  <Points>125</Points>
                </Normal>
                <Hard>
                  <Points>250</Points>
                </Hard>
                <Classic>
                  <Points>410</Points>
                </Classic>
              </PointsNeeded>
              <InactiveCosts2>
                <Off>
                  <ValueName>117952</ValueName>
                </Off>
                <On>
                  <ValueName>117955</ValueName>
                  <Points>10</Points>
                </On>
              </InactiveCosts2>
              <PermanentSectorEffects>
                <Off>
                  <ValueName>117952</ValueName>
                </Off>
                <On>
                  <ValueName>117955</ValueName>
                </On>
              </PermanentSectorEffects>
              <TemporarySectorEffects>
                <Off>
                  <ValueName>117952</ValueName>
                </Off>
                <Seldom>
                  <Points>10</Points>
                  <ValueName>121259</ValueName>
                  <Interval>1800000</Interval>
                  <TriggerProbabilityIncrease>30</TriggerProbabilityIncrease>
                  <InitialInterval>2700000</InitialInterval>
                  <InitialTriggerProbability>10</InitialTriggerProbability>
                </Seldom>
                <Regular>
                  <Points>20</Points>
                  <ValueName>121260</ValueName>
                  <Interval>1200000</Interval>
                  <TriggerProbabilityIncrease>40</TriggerProbabilityIncrease>
                  <InitialInterval>2700000</InitialInterval>
                  <InitialTriggerProbability>20</InitialTriggerProbability>
                </Regular>
                <Frequent>
                  <Points>30</Points>
                  <ValueName>121261</ValueName>
                  <Interval>600000</Interval>
                  <TriggerProbabilityIncrease>35</TriggerProbabilityIncrease>
                  <InitialInterval>1800000</InitialInterval>
                  <InitialTriggerProbability>30</InitialTriggerProbability>
                </Frequent>
              </TemporarySectorEffects>
              <NpcLevelSpeed>
                <Slow>
                  <ValueName>117958</ValueName>
                  <LevelMultiplier>1</LevelMultiplier>
                  <BalanceMultiplier>1</BalanceMultiplier>
                </Slow>
                <Normal>
                  <Points>10</Points>
                  <ValueName>117951</ValueName>
                  <LevelMultiplier>1.2</LevelMultiplier>
                  <BalanceMultiplier>1.2</BalanceMultiplier>
                </Normal>
                <Fast>
                  <Points>20</Points>
                  <ValueName>117957</ValueName>
                  <LevelMultiplier>1.5</LevelMultiplier>
                  <BalanceMultiplier>1.5</BalanceMultiplier>
                </Fast>
              </NpcLevelSpeed>
              <DominanceHiTech>
                <Off>
                  <Points>5</Points>
                </Off>
              </DominanceHiTech>
              <DominanceHeavy>
                <Off>
                  <Points>5</Points>
                </Off>
              </DominanceHeavy>
              <DominanceBiotech>
                <Off>
                  <Points>5</Points>
                </Off>
              </DominanceBiotech>
              <DominanceEnergy>
                <Off>
                  <Points>5</Points>
                </Off>
              </DominanceEnergy>
              <DominanceAgriculture>
                <Off>
                  <Points>5</Points>
                </Off>
              </DominanceAgriculture>
              <MilitarySectorEffects>
                <Off>
                  <ValueName>117952</ValueName>
                </Off>
                <Seldom>
                  <Points>10</Points>
                  <ValueName>121259</ValueName>
                  <InitialProbability>10</InitialProbability>
                  <ProbabilityIncrease>30</ProbabilityIncrease>
                  <Interval>1800000</Interval>
                </Seldom>
                <Regular>
                  <Points>15</Points>
                  <ValueName>121260</ValueName>
                  <InitialProbability>20</InitialProbability>
                  <ProbabilityIncrease>40</ProbabilityIncrease>
                  <Interval>1200000</Interval>
                </Regular>
                <Frequent>
                  <Points>20</Points>
                  <ValueName>121261</ValueName>
                  <InitialProbability>30</InitialProbability>
                  <ProbabilityIncrease>35</ProbabilityIncrease>
                  <Interval>600000</Interval>
                </Frequent>
              </MilitarySectorEffects>
              <Workforce>
                <Plenty>
                  <ValueName>117940</ValueName>
                </Plenty>
                <Medium>
                  <Points>20</Points>
                  <ValueName>117941</ValueName>
                </Medium>
                <Sparse>
                  <Points>40</Points>
                  <ValueName>117942</ValueName>
                </Sparse>
              </Workforce>
              <Consumption>
                <Sparse>
                  <ValueName>117942</ValueName>
                  <ConsumptionFactor>4096</ConsumptionFactor>
                </Sparse>
                <Medium>
                  <Points>45</Points>
                  <ValueName>117941</ValueName>
                  <ConsumptionFactor>5120</ConsumptionFactor>
                </Medium>
                <Plenty>
                  <Points>90</Points>
                  <ValueName>117940</ValueName>
                  <ConsumptionFactor>6144</ConsumptionFactor>
                </Plenty>
              </Consumption>
              <MilitaryEnemyStrength>
                <Weak>
                  <ValueName>13000556</ValueName>
                </Weak>
                <Challenging>
                  <Points>10</Points>
                  <ValueName>13000557</ValueName>
                </Challenging>
                <Deadly>
                  <Points>20</Points>
                  <ValueName>13000558</ValueName>
                </Deadly>
              </MilitaryEnemyStrength>
              <MilitaryInvasions>
                <Seldom>
                  <Points>10</Points>
                  <ValueName>121259</ValueName>
                </Seldom>
                <Regular>
                  <Points>15</Points>
                  <ValueName>121260</ValueName>
                </Regular>
                <Frequent>
                  <Points>20</Points>
                  <ValueName>121261</ValueName>
                </Frequent>
                <Off>
                  <ValueName>117952</ValueName>
                </Off>
              </MilitaryInvasions>
              <DominanceShareBonus>
                <Easy>
                  <ValueName>13000986</ValueName>
                </Easy>
                <Medium>
                  <Points>5</Points>
                  <ValueName>13000984</ValueName>
                </Medium>
                <Hard>
                  <Points>10</Points>
                  <ValueName>13000985</ValueName>
                </Hard>
              </DominanceShareBonus>
              <SatisfactionInfluencesTaxes>
                <Medium>
                  <Points>10</Points>
                  <ValueName>13000761</ValueName>
                  <TaxReductionFactor>61440</TaxReductionFactor>
                </Medium>
                <High>
                  <Points>20</Points>
                  <ValueName>13000762</ValueName>
                  <TaxReductionFactor>102400</TaxReductionFactor>
                </High>
                <None>
                  <ValueName>13000760</ValueName>
                </None>
              </SatisfactionInfluencesTaxes>
            </DifficultySettings>
          </Values>
        </Asset>
      </Assets>
    </Group>
  </Groups>
  <Assets>
    <Asset>
      <Template>PlayerCorporation</Template>
      <Values>
        <Standard>
          <GUID>2002447</GUID>
          <Name>PlayerCorporationScaling</Name>
          <Creator>mreinhardt</Creator>
          <CreationTime>2015-07-13 15:26</CreationTime>
          <LastChangeUser>Volker.Sassen</LastChangeUser>
          <LastChangeTime>2016-05-12 13:22</LastChangeTime>
          <ID>CorporationScaling</ID>
        </Standard>
        <PlayerCorporation>
          <WorldMarketRouteLimitScaling>
            <Template>CorporationScaling</Template>
            <Values>
              <CorporationScalingValue>
                <IntervalStartOffset>-45056</IntervalStartOffset>
                <Interval>40960</Interval>
                <RewardPerInterval>4096</RewardPerInterval>
                <RewardMaximum>40960</RewardMaximum>
              </CorporationScalingValue>
            </Values>
          </WorldMarketRouteLimitScaling>
          <TradeRouteAdminCostsScaling>
            <Template>CorporationScaling</Template>
            <Values>
              <CorporationScalingValue>
                <IntervalStartOffset>4096000</IntervalStartOffset>
                <Interval>4096</Interval>
                <RewardPerInterval>0</RewardPerInterval>
                <RewardIncrease>0</RewardIncrease>
                <RewardMaximum>0</RewardMaximum>
              </CorporationScalingValue>
            </Values>
          </TradeRouteAdminCostsScaling>
          <StartInfluence>60</StartInfluence>
          <StartInfluenceRankModifier>1.2</StartInfluenceRankModifier>
          <InfluenceRankModifier>-0.1</InfluenceRankModifier>
          <InfluencePerLevel>0.3</InfluencePerLevel>
        </PlayerCorporation>
      </Values>
    </Asset>
    <Asset>
      <Template>EconomicWarfareFeature</Template>
      <Values>
        <Standard>
          <GUID>2002493</GUID>
          <Name>EconomicWarfare</Name>
          <Creator>rkenzler</Creator>
          <CreationTime>2016-03-04 15:24</CreationTime>
          <LastChangeUser>cschneider</LastChangeUser>
          <LastChangeTime>2016-08-18 12:41</LastChangeTime>
          <ID>EconomicWarfare</ID>
        </Standard>
        <EconomicWarfareFeature>
          <LowerLevelScale>0.8</LowerLevelScale>
          <UpperLevelScale>1.2</UpperLevelScale>
          <LowerLevelRange>5</LowerLevelRange>
          <UpperLevelRange>5</UpperLevelRange>
          <StartBalanceModifier>1.3</StartBalanceModifier>
          <BalanceRankModifier>0.1</BalanceRankModifier>
          <ShareValue>
            <Template>CorporationScaling</Template>
            <Values>
              <CorporationScalingValue>
                <Interval>4096</Interval>
                <RewardPerInterval>81920000</RewardPerInterval>
                <RewardMaximum>61440000000</RewardMaximum>
                <RewardOffset>3072000000</RewardOffset>
              </CorporationScalingValue>
            </Values>
          </ShareValue>
          <FreeShareValue>60</FreeShareValue>
          <EnemyShareValue>90</EnemyShareValue>
          <FirstShareValueBonus>4</FirstShareValueBonus>
          <StartShareModifier>1</StartShareModifier>
          <ShareOwnedModifier>0.1</ShareOwnedModifier>
          <InfluenceActivationGeneration>
            <Template>CorporationScaling</Template>
            <Values>
              <CorporationScalingValue>
                <IntervalStartOffset>-4096</IntervalStartOffset>
                <Interval>4096</Interval>
                <RewardPerInterval>4096</RewardPerInterval>
                <RewardMaximum>405504</RewardMaximum>
                <RewardOffset>102400</RewardOffset>
              </CorporationScalingValue>
            </Values>
          </InfluenceActivationGeneration>
          <XpRequirementFactor>1.8</XpRequirementFactor>
          <XpRequirementTimeOffset>900</XpRequirementTimeOffset>
          <InfluenceConversion>
            <Item>
              <GainedInfluence>1</GainedInfluence>
            </Item>
            <Item>
              <CreditStartRange>2000</CreditStartRange>
              <GainedInfluence>2</GainedInfluence>
            </Item>
            <Item>
              <CreditStartRange>3000</CreditStartRange>
              <GainedInfluence>3</GainedInfluence>
            </Item>
            <Item>
              <CreditStartRange>4000</CreditStartRange>
              <GainedInfluence>4</GainedInfluence>
            </Item>
            <Item>
              <CreditStartRange>5000</CreditStartRange>
              <GainedInfluence>5</GainedInfluence>
            </Item>
            <Item>
              <CreditStartRange>6000</CreditStartRange>
              <GainedInfluence>6</GainedInfluence>
            </Item>
            <Item>
              <CreditStartRange>7000</CreditStartRange>
              <GainedInfluence>7</GainedInfluence>
            </Item>
            <Item>
              <CreditStartRange>8000</CreditStartRange>
              <GainedInfluence>8</GainedInfluence>
            </Item>
            <Item>
              <CreditStartRange>9000</CreditStartRange>
              <GainedInfluence>9</GainedInfluence>
            </Item>
            <Item>
              <CreditStartRange>10000</CreditStartRange>
              <GainedInfluence>10</GainedInfluence>
            </Item>
            <Item>
              <CreditStartRange>11000</CreditStartRange>
              <GainedInfluence>11</GainedInfluence>
            </Item>
            <Item>
              <CreditStartRange>20000</CreditStartRange>
              <GainedInfluence>12</GainedInfluence>
            </Item>
            <Item>
              <CreditStartRange>30000</CreditStartRange>
              <GainedInfluence>13</GainedInfluence>
            </Item>
            <Item>
              <CreditStartRange>40000</CreditStartRange>
              <GainedInfluence>14</GainedInfluence>
            </Item>
            <Item>
              <CreditStartRange>50000</CreditStartRange>
              <GainedInfluence>15</GainedInfluence>
            </Item>
            <Item>
              <CreditStartRange>60000</CreditStartRange>
              <GainedInfluence>16</GainedInfluence>
            </Item>
            <Item>
              <CreditStartRange>70000</CreditStartRange>
              <GainedInfluence>17</GainedInfluence>
            </Item>
            <Item>
              <CreditStartRange>80000</CreditStartRange>
              <GainedInfluence>18</GainedInfluence>
            </Item>
            <Item>
              <CreditStartRange>90000</CreditStartRange>
              <GainedInfluence>20</GainedInfluence>
            </Item>
            <Item>
              <CreditStartRange>100000</CreditStartRange>
              <GainedInfluence>25</GainedInfluence>
            </Item>
            <Item>
              <CreditStartRange>500000</CreditStartRange>
              <GainedInfluence>30</GainedInfluence>
            </Item>
            <Item>
              <CreditStartRange>1000000</CreditStartRange>
              <GainedInfluence>40</GainedInfluence>
            </Item>
            <Item>
              <CreditStartRange>2000000</CreditStartRange>
              <GainedInfluence>50</GainedInfluence>
            </Item>
            <Item>
              <CreditStartRange>5000000</CreditStartRange>
              <GainedInfluence>65</GainedInfluence>
            </Item>
            <Item>
              <CreditStartRange>10000000</CreditStartRange>
              <GainedInfluence>85</GainedInfluence>
            </Item>
          </InfluenceConversion>
          <AIStrategyTickMin>225000</AIStrategyTickMin>
          <AIStrategyTickMax>330000</AIStrategyTickMax>
          <AIStrategyTickRoot>14000978</AIStrategyTickRoot>
          <AIAuctionTickMin>1000</AIAuctionTickMin>
          <AIAuctionTickMax>1000</AIAuctionTickMax>
          <AIAuctionTickRoot>14001186</AIAuctionTickRoot>
          <DominanceThreshold>0.75</DominanceThreshold>
          <PlayerDominanceMultiplier>
            <HiTech>
              <Multiplier>4</Multiplier>
            </HiTech>
            <Heavy>
              <Multiplier>5</Multiplier>
            </Heavy>
            <Biotech>
              <Multiplier>4</Multiplier>
            </Biotech>
            <Energy>
              <Multiplier>3</Multiplier>
            </Energy>
            <Agriculture>
              <Multiplier>6</Multiplier>
            </Agriculture>
          </PlayerDominanceMultiplier>
          <InfluenceMultiplier>
            <Easy>
              <BonusByShare>3</BonusByShare>
              <BonusBySet>10</BonusBySet>
            </Easy>
            <Medium>
              <BonusByShare>2</BonusByShare>
              <BonusBySet>5</BonusBySet>
            </Medium>
            <Hard>
              <BonusByShare>1</BonusByShare>
            </Hard>
          </InfluenceMultiplier>
        </EconomicWarfareFeature>
      </Values>
    </Asset>
    <Asset>
      <Template>SimulationFeature</Template>
      <Values>
        <Standard>
          <GUID>2002473</GUID>
          <Name>SimulationFeature</Name>
          <Creator>mreinhardt</Creator>
          <CreationTime>2016-02-29 14:37</CreationTime>
          <LastChangeUser>cschneider</LastChangeUser>
          <LastChangeTime>2016-03-04 11:48</LastChangeTime>
          <ID>SimulationFeature</ID>
        </Standard>
        <SimulationFeature>
          <MetropolisFactorScaling>
            <Template>CorporationScaling</Template>
            <Values>
              <CorporationScalingValue>
                <Interval>40960000</Interval>
                <RewardPerInterval>20</RewardPerInterval>
                <RewardMaximum>1024</RewardMaximum>
              </CorporationScalingValue>
            </Values>
          </MetropolisFactorScaling>
        </SimulationFeature>
      </Values>
    </Asset>
  </Assets>
</Group>